axualclient/__init__.py
axualclient/avro.py
axualclient/axual_consumer.py
axualclient/axual_producer.py
axualclient/consumer.py
axualclient/deserializing_consumer.py
axualclient/discovery.py
axualclient/exception.py
axualclient/patterns.py
axualclient/producer.py
axualclient/serializing_producer.py
axualclient/util.py
axualclient/version.py
axual_client_python-1.1.5.dist-info/LICENSE
axual_client_python-1.1.5.dist-info/WHEEL
axual_client_python-1.1.5.dist-info/METADATA
axual_client_python-1.1.5.dist-info/RECORD
