Metadata-Version: 2.1
Name: axual-client-python
Version: 1.1.5
Summary: Axual client for Python
License: Apache-2.0
Author: Axual
Author-email: opensource@axual.com
Requires-Python: >=3.6,<4.0
Classifier: License :: OSI Approved :: Apache Software License
Classifier: Programming Language :: Python :: 3
Classifier: Programming Language :: Python :: 3.10
Classifier: Programming Language :: Python :: 3.6
Classifier: Programming Language :: Python :: 3.7
Classifier: Programming Language :: Python :: 3.8
Classifier: Programming Language :: Python :: 3.9
Requires-Dist: confluent-kafka[avro] (>=1.7.0,<2.0.0)
